setup.cfg
setup.py
var_control/LinearDecorrelator.py
var_control/PolynomialDecorrelator.py
var_control/__init__.py
var_control.egg-info/PKG-INFO
var_control.egg-info/SOURCES.txt
var_control.egg-info/dependency_links.txt
var_control.egg-info/not-zip-safe
var_control.egg-info/top_level.txt