Metadata-Version: 1.0
Name: var-control
Version: 0.3.1
Summary: Decorrelates variable from a pandas dataframe.
Home-page: https://github.com/eddbrown/var_control
Author: Edward Brown
Author-email: edward.j.e.brown@gmail.com
License: UNKNOWN
Platform: UNKNOWN
